incidental/cli.py
incidental-0.0.1.dist-info/LICENSE
incidental-0.0.1.dist-info/WHEEL
incidental-0.0.1.dist-info/METADATA
incidental-0.0.1.dist-info/RECORD
