Metadata-Version: 2.1
Name: incidental
Version: 0.0.1
Summary: 
License: MIT
Author: cloudcraeft
Author-email: cloudcraeft@outlook.com
Requires-Python: >=3.7,<4.0
Classifier: License :: OSI Approved :: MIT License
Classifier: Programming Language :: Python :: 3
Classifier: Programming Language :: Python :: 3.7
Requires-Dist: invoke (>=1.3,<2.0)
